exo_predict/__init__.py
exo_predict/exo_model_predict.py
exo_predict/exo_predict.py
exo_predict/data/num_planets_model.p
exo_predict-1.0.27.dist-info/METADATA
exo_predict-1.0.27.dist-info/WHEEL
exo_predict-1.0.27.dist-info/top_level.txt
exo_predict-1.0.27.dist-info/RECORD
